LICENSE
MANIFEST.in
README.md
setup.py
stylus/__init__.py
stylus/compiler.js
stylus/runner.js
stylus.egg-info/PKG-INFO
stylus.egg-info/SOURCES.txt
stylus.egg-info/dependency_links.txt
stylus.egg-info/pbr.json
stylus.egg-info/requires.txt
stylus.egg-info/top_level.txt