Metadata-Version: 1.1
Name: stylus
Version: 0.1.2
Summary: A bridge to the Stylus css compiler
Home-page: https://github.com/bkad/python-stylus
Author: Kevin Le
Author-email: solnovus@gmail.com
License: MIT License
Platform: UNKNOWN
Classifier: Development Status :: 3 - Alpha
Classifier: Programming Language :: Python :: 2
Classifier: Programming Language :: Python :: 2.7
